LICENSE
README.md
VERSION
pyproject.toml
requirements.txt
src/icc_generator/VERSION
src/icc_generator/__init__.py
src/icc_generator/api.py
src/icc_generator/ui.py
src/icc_generator/version.py
src/icc_generator.egg-info/PKG-INFO
src/icc_generator.egg-info/SOURCES.txt
src/icc_generator.egg-info/dependency_links.txt
src/icc_generator.egg-info/requires.txt
src/icc_generator.egg-info/top_level.txt
tests/test_ICCGenerator.py
tests/test_paper_size.py
tests/test_paper_size_library.py
tests/test_patch_count.py