Metadata-Version: 2.2
Name: icc_generator
Version: 0.8.0
Summary: A Python module that lets the users to create Printer Profiles with Argyll CMS and X-Rite ColorMunki Photo and X-Rite i1Pro 2/3
Author-email: Erkan Özgür Yılmaz <eoyilmaz@gmail.com>
Maintainer-email: Erkan Özgür Yılmaz <eoyilmaz@gmail.com>
License: Copyright 2019-2021 Erkan Ozgur Yilmaz
Project-URL: Home Page, https://github.com/eoyilmaz/argyll_printer_profiling
Project-URL: GitHub, https://github.com/eoyilmaz/argyll_printer_profiling
Project-URL: Repository, https://github.com/eoyilmaz/argyll_printer_profiling.git
Keywords: argyll,cms,color,colour,management,printer,profile,profiling,calibration
Classifier: Programming Language :: Python
Classifier: Programming Language :: Python :: 3.8
Classifier: Programming Language :: Python :: 3.9
Classifier: Programming Language :: Python :: 3.10
Classifier: Programming Language :: Python :: 3.11
Classifier: Programming Language :: Python :: 3.12
Classifier: Programming Language :: Python :: 3.13
Classifier: License :: OSI Approved :: MIT License
Classifier: Operating System :: OS Independent
Classifier: Development Status :: 5 - Production/Stable
Classifier: Intended Audience :: End Users/Desktop
Classifier: Topic :: Printing
Classifier: Topic :: Utilities
Requires-Python: >=3.8
License-File: LICENSE
Requires-Dist: build
Requires-Dist: prettytable
